syncInput.v
module syncInput(
  input clk,
  input btn,
  output reg syncBtn = 0
);
    reg b1;
    reg b2;
    always @(posedge clk) begin
      b1 <= btn;
      b2 <= b1;
      if (b1 && !b2) begin
        syncBtn <= 1;
      end
      if (!b1 && b2) begin
        syncBtn <= 0;
      end
    end
endmodule // syncInput

t_input.v
`timescale 1ns/1ps
module test(
);
    reg clk;
    reg btn;
    wire syncBtn;
    initial begin
      clk = 0;
      forever #0.8 clk = ~clk;
    end
    syncInput t (clk, btn, syncBtn);
    initial begin
      $dumpfile("test.vcd");
      $dumpvars;
      btn = 0;
      #2 btn = 1;
      #4 btn = 0;
      #5 btn = 1;
      #2 btn = 0;
      #5 btn = 1;
      #4 btn = 0;
      #6 btn = 1;
      #2 btn = 0;
    end
    initial #500 $finish;
endmodule // test

test.vcd
$date
	Thu Jun  8 01:04:06 2017
$end
$version
	Icarus Verilog
$end
$timescale
	1ps
$end
$scope module test $end
$var wire 1 ! syncBtn $end
$var reg 1 " btn $end
$var reg 1 # clk $end
$scope module t $end
$var wire 1 " btn $end
$var wire 1 # clk $end
$var reg 1 $ b1 $end
$var reg 1 % b2 $end
$var reg 1 ! syncBtn $end
$upscope $end
$upscope $end
$enddefinitions $end
#0
$dumpvars
x%
x$
0#
0"
0!
$end
#800
0$
1#
#1600
0#
#2000
1"
#2400
0%
1$
1#
#3200
0#
#4000
1!
1%
1#
#4800
0#
#5600
1#
#6000
0"
#6400
0#
#7200
0$
1#
#8000
0#
#8800
0!
0%
1#
#9600
0#
#10400
1#
#11000
1"
#11200
0#
#12000
1$
1#
#12800
0#
#13000
0"
#13600
1!
1%
0$
1#
#14400
0#
#15200
0!
0%
1#
#16000
0#
#16800
1#
#17600
0#
#18000
1"
#18400
1$
1#
#19200
0#
#20000
1!
1%
1#
#20800
0#
#21600
1#
#22000
0"
#22400
0#
#23200
0$
1#
#24000
0#
#24800
0!
0%
1#
#25600
0#
#26400
1#
#27200
0#
#28000
1$
1#
1"
#28800
0#
#29600
1!
1%
1#
#30000
0"
#30400
0#
#31200
0$
1#
#32000
0#
#32800
0!
0%
1#
