ShowView.v
`timescale 1ns / 1ps

module ShowView(
    input clk,
    input [5:0] uTot,
    input [5:0] uCur,
    input [5:0] uWat,
    output [7:0] ySEG_,
    output [7:0] yAN_
);
    wire [2:0] xPos;
    wire [3:0] xVal;
    wire [3:0] xMem[7:0];
    _disp_counter   vC8(clk, xPos);
    _disp_decimal   vDecTot(uTot, xMem[7], xMem[6]);
    _disp_decimal   vDecCur(uCur, xMem[4], xMem[3]);
    assign xMem[5] = 4'hf;
    assign xMem[2] = 4'hf;
    _disp_decimal   vDecWat(uWat, xMem[1], xMem[0]);
    _disp_pattern   vPat(xMem[xPos], ySEG_);
    _disp_position  vPos(xPos, yAN_);
endmodule

module _disp_counter(
    input clk,
    output reg [2:0] yVal = 3'b000
);
    always @(posedge clk)
        yVal <= yVal + 1;
endmodule

module _disp_decimal(
    input [5:0] uVal,
    output [3:0] yE1,
    output [3:0] yE2
);
    assign yE1 = (uVal == 55) ? 4'hf :
                 (uVal == 56) ? 8 : 
                 (uVal == 57) ? 10 : 
                 (uVal == 58) ? 12 : uVal / 10;
    assign yE2 = (uVal == 55) ? 4'hf :
                 (uVal == 56) ? 8 :
                 (uVal == 57) ? 11 : 
                 (uVal == 58) ? 11 : uVal % 10;
endmodule

module _disp_pattern(
    input [3:0] uVal,
    output reg [7:0] ySEG_
);
    always @(uVal)
        case (uVal)
            'b0000:  ySEG_ <= 'b11000000;
            'b0001:  ySEG_ <= 'b11111001;
            'b0010:  ySEG_ <= 'b10100100;
            'b0011:  ySEG_ <= 'b10110000;
            'b0100:  ySEG_ <= 'b10011001;
            'b0101:  ySEG_ <= 'b10010010;
            'b0110:  ySEG_ <= 'b10000010;
            'b0111:  ySEG_ <= 'b11111000;
            'b1000:  ySEG_ <= 'b10000000;
            'b1001:  ySEG_ <= 'b10010000;
            'b1010:  ySEG_ <= 'b10001100;
            'b1011:  ySEG_ <= 'b10001000;
            'b1100:  ySEG_ <= 'b10000110;
            default: ySEG_ <= 'b11111111;
        endcase
endmodule

module _disp_position(
    input [2:0] uPos,
    output [7:0] yAN_
);
    assign yAN_ = ~(8'b1 << uPos);
endmodule // ShowView

View.v
`timescale 1ns/1ps
module View(
  cp,
  state,
  data,
  inLeft, inMiddle, inRight,
  showLeft, showRight,

  w_inWaterLED,
  w_WLED,
  r_outWaterLED,
  r_spinWaterLED,
  r_inWaterLED,
  r_RLED,
  d_outwaterLED,
  d_spinWaterLED,

  setLED,
  powerLED
);
    input cp;
    input [2:0] state;
    input [9:0] data;
    input [5:0] inLeft;
    input [5:0] inMiddle;
    input [5:0] inRight;

    output [7:0] showLeft;
    output [7:0] showRight;
    
    output w_inWaterLED;
    output w_WLED;
    output r_outWaterLED;
    output r_spinWaterLED;
    output r_inWaterLED;
    output r_RLED;
    output d_outwaterLED;
    output d_spinWaterLED;
    output setLED;
    output powerLED;

    wire [5:0] left;
    wire [5:0] middle;
    wire [5:0] right;

    localparam shutDownST = 0, beginST = 1, setST = 2, runST = 3;
    localparam errorST = 4, pauseST = 5, finishST = 6;

    localparam showEmpty = 55, showFull = 56, showPause = 57;
    
    assign left = (state == shutDownST) ? showEmpty :
                  (state == beginST) ? showFull :
                  (state == finishST) ? showFull : inLeft;
    assign right = (state == shutDownST) ? showEmpty :
                   (state == beginST) ? showFull :
                   (state == finishST) ? showFull : inRight;
    assign middle = (state == shutDownST) ? showEmpty :
                    (state == beginST) ? showFull : 
                    (state == finishST) ? showFull :
                    (state == pauseST) ? showPause : inMiddle;
    assign w_inWaterLED = (state == shutDownST) ? 1 :
                          (state == beginST) ? 0 :
                          (state == finishST) ? 1 : data[7];
    assign w_WLED = (state == shutDownST) ? 1 :
                    (state == beginST) ? 0 :
                    (state == finishST) ? 1 : data[6];
    assign r_outWaterLED = (state == shutDownST) ? 1 :
                           (state == beginST) ? 0 :
                           (state == finishST) ? 1 : data[5];
    assign r_spinWaterLED = (state == shutDownST) ? 1 :
                            (state == beginST) ? 0 :
                            (state == finishST) ? 1 : data[4];
    assign r_inWaterLED = (state == shutDownST) ? 1 :
                          (state == beginST) ? 0 :
                          (state == finishST) ? 1 : data[3];
    assign r_RLED = (state == shutDownST) ? 1 :
                    (state == beginST) ? 0 :
                    (state == finishST) ? 1 : data[2];
    assign d_outwaterLED = (state == shutDownST) ? 1 :
                           (state == beginST) ? 0 :
                           (state == finishST) ? 1 : data[1];
    assign d_spinWaterLED = (state == shutDownST) ? 1 :
                            (state == beginST) ? 0 :
                            (state == finishST) ? 1 : data[0];

    assign powerLED = data[8];
    assign setLED = data[9];

    ShowView l (cp, left, middle, right, showLeft, showRight);

endmodule // View

ViewController.v
`timescale 1ns/1ps
module ViewController(
  cp,
  state,
  msg,
  showLeft,
  showMiddle,
  showRight,
  LEDMsg
);
    input cp;
    input [2:0] state;
    input [25:0] msg;
    output wire [5:0] showLeft;
    output wire [5:0] showMiddle;
    output wire [5:0] showRight;
    output wire [9:0] LEDMsg;

    localparam shutDownST = 0, beginST = 1, setST = 2, runST = 3;
    localparam errorST = 4, pauseST = 5, finishST = 6;

    assign showLeft = msg[25:23]+msg[22:19]+msg[18:16]+msg[15:13]+msg[12:10]+msg[9:6]+msg[5:3]+msg[2:0];
    assign showMiddle = (msg[25:23] != 0)? msg[25:23] :
                        (msg[22:19] != 0)? msg[22:19] :
                        (msg[18:16] != 0)? msg[18:16] :
                        (msg[15:13] != 0)? msg[15:13] :
                        (msg[12:10] != 0)? msg[12:10] :
                        (msg[9:6] != 0)? msg[9:6] :
                        (msg[5:3] != 0)? msg[5:3] :
                        (msg[2:0] != 0)? msg[2:0] : 0;
    assign showRight = msg[25:23];

    assign LEDMsg[0] = (msg[2:0] == 0) ? 0 : 1;
    assign LEDMsg[1] = (msg[5:3] == 0) ? 0 : 1;
    assign LEDMsg[2] = (msg[9:6] == 0) ? 0 : 1;
    assign LEDMsg[3] = (msg[12:10] == 0) ? 0 : 1;
    assign LEDMsg[4] = (msg[15:13] == 0) ? 0 : 1;
    assign LEDMsg[5] = (msg[18:16] == 0) ? 0 : 1;
    assign LEDMsg[6] = (msg[22:19] == 0) ? 0 : 1;
    assign LEDMsg[7] = (msg[25:23] == 0) ? 0 : 1;
    assign LEDMsg[8] = (state == shutDownST) ? 0 : 1;
    assign LEDMsg[9] = (state == setST) ? 1 : 0;


endmodule // ViewController

RunController.v
`timescale 1ns/1ps
module RunController(
  clk,
  state,
  data,
  hadFinish,
  initTime,
  finishTime,
  msg
);
    input clk;
    input [2:0] state;
    input [25:0] data;
    output reg hadFinish = 0;
    output reg [2:0] initTime = 5;
    output reg [2:0] finishTime = 5;
    output reg [25:0] msg = 0;
    parameter shutDownST = 0, beginST = 1, setST = 2, runST = 3;
    parameter errorST = 4, pauseST = 5, finishST = 6;

    second s (clk, cp);

    always @(posedge cp) begin
     if (state == runST) begin
       if (msg[25:23] != 0)
        msg[25:23] <= msg[25:23] - 1;
       else if (msg[22:19] != 0) 
        msg[22:19] <= msg[22:19] - 1;
       else if (msg[18:16] != 0)
        msg[18:16] <= msg[18:16] - 1;
       else if (msg[15:13] != 0)
        msg[15:13] <= msg[15:13] - 1;
       else if (msg[12:10] != 0)
        msg[12:10] <= msg[12:10] - 1;
       else if (msg[9:6] != 0) 
        msg[9:6] <= msg[9:6] - 1;
       else if (msg[5:3] != 0)
        msg[5:3] <= msg[5:3] - 1;
       else if (msg[2:0] != 0)
        msg[2:0] <= msg[2:0] - 1;
       else 
        hadFinish <= 1;
       finishTime <= 5;
       initTime <= 5;
     end
     else if (state == beginST) begin
       initTime <= initTime - 1;
       finishTime <= 5;
       msg <= data;
       hadFinish <= 0;
     end
     else if (state == finishST) begin
       finishTime <= finishTime - 1;
       initTime <= 5;
       msg <= data;
       hadFinish <= 0;
     end
     else if (state == pauseST) begin
       finishTime <= 5;
       initTime <= 5;
       msg <= msg;
       hadFinish <= 0;
     end
     else begin
       finishTime <= 5;
       initTime <= 5;
       msg <= data;
       hadFinish <= 0;
     end
    end
endmodule // RunController

module second(
  input clk,
  output reg cp
);
    parameter delay = 5;
    integer count = 0;
    initial begin
      cp = 1;
    end
    always @(posedge clk) begin
      count = count + 1;
      if (count == delay) begin
        cp = ~cp;
        count = 0;
      end
    end
endmodule // second

Model.v
`timescale 1ns/1ps
module Model(
  cp, 
  click,
  waterBtn,
  state,
  setData,
  outData
);
    input cp;
    input click;
    input waterBtn;
    input [2:0] state;
    output reg [2:0] setData;
    output [25:0] outData;

    localparam shutDownST = 0, beginST = 1, setST = 2, runST = 3;
    localparam errorST = 4, pauseST = 5, finishST = 6;

    localparam set_WRD_ST = 0, set_W_ST = 1, set_WR_ST = 2;
    localparam set_R_ST = 3, set_RD_ST = 4, set_D_ST = 5, set_USE_ST = 6;

    reg [2:0] inWaterTime;
    wire [2:0] setting;
    wire [25:0] data;

    assign setting = setData;

    getTime t (setting, inWaterTime, data);

    select s (state, setting, data, outData);

    always @(posedge cp) begin
      if (state == setST && click && !waterBtn) begin
        setData <= (setData == set_USE_ST) ? set_WRD_ST : setData + 1;
        inWaterTime <= 3;
      end
      else if (state == setST && click && waterBtn) begin
        setData <= set_USE_ST;
        inWaterTime <= (inWaterTime == 7) ? 7 : inWaterTime + 1;
      end
      else if (state == beginST) begin
        setData <= 0;
        inWaterTime <= 3;
      end
      else begin
        setData <= setData;
        inWaterTime <= inWaterTime;
      end
    end
endmodule // Model

module getTime(
  setData,
  inWaterTime,
  getData
);
    input [2:0] setData;
    input [2:0] inWaterTime;
    output reg [25:0] getData;

    localparam set_WRD_ST = 0, set_W_ST = 1, set_WR_ST = 2;
    localparam set_R_ST = 3, set_RD_ST = 4, set_D_ST = 5, set_USE_ST = 6;

    always @(*) begin
      case (setData)
        set_WRD_ST: begin
          getData <= 26'b011_1010_100_101_011_1000_100_101;
        end
        set_W_ST: begin
          getData <= 26'b011_1010_000_000_000_0000_000_000;
        end 
        set_WR_ST: begin
          getData <= 26'b011_1010_100_101_011_1000_000_000;
        end
        set_R_ST: begin
          getData <= 26'b000_0000_100_101_011_1000_000_000;
        end
        set_RD_ST: begin
          getData <= 26'b000_0000_100_101_011_1000_100_101;
        end
        set_D_ST: begin
          getData <= 26'b000_0000_000_000_000_0000_100_101;
        end
        set_USE_ST: begin
          getData <= {inWaterTime, 4'b1010, 3'b100, 3'b101, inWaterTime, 4'b1000, 3'b100, 3'b101};
        end
      endcase
    end
endmodule // getTime

module select(
  state,
  setData,
  data,
  res
);
  input [2:0] state;
  input [2:0] setData;
  input [25:0] data;
  output wire [25:0] res;

  localparam shutDownST = 0, beginST = 1, setST = 2, runST = 3;
  localparam errorST = 4, pauseST = 5, finishST = 6;

  localparam set_WRD_ST = 0, set_W_ST = 1, set_WR_ST = 2;
  localparam set_R_ST = 3, set_RD_ST = 4, set_D_ST = 5, set_USE_ST = 6;
  assign res = (state != setST) ? data :
               (state == beginST) ? 0 :
               (setData == set_WRD_ST) ? 26'b000_0000_000_000_000_0001_001_001 :
               (setData == set_W_ST) ?   26'b000_0000_000_000_000_0001_000_000 : 
               (setData == set_WR_ST) ?  26'b000_0000_000_000_000_0001_001_000 :
               (setData == set_R_ST) ?   26'b000_0000_000_000_000_0000_001_000 :
               (setData == set_RD_ST) ?  26'b000_0000_000_000_000_0000_001_001 :
               (setData == set_D_ST) ?   26'b000_0000_000_000_000_0000_000_001 :
               (setData == set_USE_ST) ? 26'b000_0000_000_000_000_0001_001_001 : data;
endmodule // select

STController.v
`timescale 1ns/1ps
module STController(
  cp, 
  resetBtn, runBtn, openBtn,
  hadFinish, 
  initTime, finishTime,
  state
);
    input cp;
    input resetBtn, runBtn, openBtn;
    input hadFinish;
    input [2:0] initTime;
    input [2:0] finishTime;

    output reg [2:0]state;

    parameter shutDownST = 0, beginST = 1, setST = 2, runST = 3;
    parameter errorST = 4, pauseST = 5, finishST = 6;

    reg [2:0] nextState;
    always @(posedge cp) begin
      if (resetBtn == 0) begin
        state <= shutDownST;
      end
      else begin
        state <= nextState;
      end
    end
    always @(*) begin
      case (state)
        shutDownST: begin
          if (resetBtn) begin
            nextState = beginST;
          end
          else begin
            nextState = shutDownST;
          end
        end
        beginST: begin
          if (initTime > 0) begin
            nextState = beginST;
          end
          else begin
            nextState = setST;
          end
        end
        setST: begin
          if (runBtn) begin
            nextState = runBtn;
          end
          else begin
            nextState = setST;
          end
        end
        runST: begin
          if (!runBtn) begin
            nextState = pauseST;
          end
          else if (openBtn) begin
            nextState = pauseST;
          end
          else if (hadFinish) begin
            nextState = finishST;
          end
          else begin
            nextState = runST;
          end
        end
        finishST: begin
          if (finishTime > 0) begin
            nextState = finishST;
          end
          else begin
            nextState = shutDownST;
          end
        end
      endcase
    end
endmodule // STController

syncInput.v
module syncInput(
  input clk,
  input btn,
  output reg syncBtn = 0
);
    reg b1;
    reg b2;
    always @(posedge clk) begin
      b1 <= btn;
      b2 <= b1;
      if (b1 && !b2) begin
        syncBtn <= 1;
      end
      if (!b1 && b2) begin
        syncBtn <= 0;
      end
    end
endmodule // syncInput

syncClock.v
module syncClock(
  input clk,
  output reg cp
);
    localparam delay = 5; //5000
    integer counter = 0;
    initial begin
      cp = 0;
    end
    always @(posedge clk) begin
      counter = counter + 1;
      if (counter == delay) begin
        cp = ~cp;
        counter = 0;
      end
    end
endmodule // syncClock

washer.v
`timescale 1ns / 1ps
module Washer(
  clk,
  w_inWaterLED,
  w_WLED,
  r_outWaterLED,
  r_spinWaterLED,
  r_inWaterLED,
  r_RLED,
  d_outwaterLED,
  d_spinWaterLED,
  setLED,
  powerLED,

  out_showL, out_showR,

  in_resetBtn,
  in_runBtn,
  in_WaterBtn,
  in_openBtn,
  in_click
);
    input clk;
    output w_inWaterLED;
    output w_WLED;
    output r_outWaterLED;
    output r_spinWaterLED;
    output r_inWaterLED;
    output r_RLED;
    output d_outwaterLED;
    output d_spinWaterLED;
    output setLED;
    output powerLED;

    output wire [7:0] out_showL, out_showR;

    input in_resetBtn;
    input in_runBtn;
    input in_WaterBtn;
    input in_openBtn;
    input in_click;

    wire resetBtn;
    wire runBtn;
    wire WaterBtn;
    wire openBtn;
    wire click;

    wire cp;
    syncClock c (clk, cp);

    syncInput b1 (cp, in_resetBtn, resetBtn);
    syncInput b2 (cp, in_runBtn, runBtn);
    syncInput b6 (cp, in_WaterBtn, WaterBtn);
    syncInput b7 (cp, in_openBtn, openBtn);
    syncInput b8 (cp, in_click, click);


    wire [2:0] state;
    wire hadFinish;
    wire [2:0] initTime;
    wire [2:0] finishTime;
    wire [2:0] setData;
    wire [25:0] data;
    wire [25:0] msg;
    wire [5:0] showLeft;
    wire [5:0] showMiddle;
    wire [5:0] showRight;
    wire [9:0] LEDMsg;


    STController stc (cp, resetBtn, runBtn, openBtn, hadFinish, initTime, finishTime, state);
    Model m (cp, click, WaterBtn, state, setData, data);
    RunController rc (cp, state, data, hadFinish, initTime, finishTime, msg);
    ViewController vc (cp, state, msg, showLeft, showMiddle, showRight, LEDMsg);
    View v (cp, state, LEDMsg, showLeft, showMiddle, showRight, out_showL, out_showR, w_inWaterLED, w_WLED, r_outWaterLED, r_spinWaterLED, r_inWaterLED, r_RLED, d_outwaterLED, d_spinWaterLED, setLED, powerLED);

endmodule // Washer

t_washer.v
`timescale 1ns / 1ps
module test(
);
  reg clk;
  wire w_inWaterLED;
  wire w_WLED;
  wire r_outWaterLED;
  wire r_spinWaterLED;
  wire r_inWaterLED;
  wire r_RLED;
  wire d_outwaterLED;
  wire d_spinWaterLED;
  wire setLED;
  wire powerLED;

  wire [7:0] out_showL, out_showR;

  reg in_resetBtn;
  reg in_runBtn;
  reg in_WBtn, in_RBtn, in_DBtn, in_WaterBtn;
  reg in_openBtn;
  reg in_click;

  initial begin
    clk = 1;
    forever #0.05 clk = ~clk;
  end
  Washer t (clk, w_inWaterLED, w_WLED, r_outWaterLED, r_spinWaterLED, r_inWaterLED, r_RLED, d_outwaterLED, d_spinWaterLED, setLED, powerLED, out_showL, out_showR, in_resetBtn, in_runBtn, in_WaterBtn, in_openBtn, in_click);
  initial begin
      $dumpfile("test.vcd");
      $dumpvars;
      in_resetBtn = 0;
      in_runBtn = 0;
      in_WaterBtn = 0;
      in_openBtn = 0;
      in_click = 0;

      #50 in_resetBtn = 1;
      #50 in_click = 1;
      #1.5 in_click = 0;
      #10 in_runBtn = 1;
      #2000 in_openBtn = 1;
      #30 in_openBtn = 0;
  end
  initial #8800 $finish;
endmodule // test

test.vcd
$date
	Thu Jun  8 10:06:47 2017
$end
$version
	Icarus Verilog
$end
$timescale
	1ps
$end
$scope module test $end
$var wire 1 ! w_inWaterLED $end
$var wire 1 " w_WLED $end
$var wire 1 # setLED $end
$var wire 1 $ r_spinWaterLED $end
$var wire 1 % r_outWaterLED $end
$var wire 1 & r_inWaterLED $end
$var wire 1 ' r_RLED $end
$var wire 1 ( powerLED $end
$var wire 8 ) out_showR [7:0] $end
$var wire 8 * out_showL [7:0] $end
$var wire 1 + d_spinWaterLED $end
$var wire 1 , d_outwaterLED $end
$var reg 1 - clk $end
$var reg 1 . in_WaterBtn $end
$var reg 1 / in_click $end
$var reg 1 0 in_openBtn $end
$var reg 1 1 in_resetBtn $end
$var reg 1 2 in_runBtn $end
$scope module t $end
$var wire 1 - clk $end
$var wire 1 . in_WaterBtn $end
$var wire 1 / in_click $end
$var wire 1 0 in_openBtn $end
$var wire 1 1 in_resetBtn $end
$var wire 1 2 in_runBtn $end
$var wire 1 ! w_inWaterLED $end
$var wire 1 " w_WLED $end
$var wire 3 3 state [2:0] $end
$var wire 6 4 showRight [5:0] $end
$var wire 6 5 showMiddle [5:0] $end
$var wire 6 6 showLeft [5:0] $end
$var wire 1 # setLED $end
$var wire 3 7 setData [2:0] $end
$var wire 1 8 runBtn $end
$var wire 1 9 resetBtn $end
$var wire 1 $ r_spinWaterLED $end
$var wire 1 % r_outWaterLED $end
$var wire 1 & r_inWaterLED $end
$var wire 1 ' r_RLED $end
$var wire 1 ( powerLED $end
$var wire 8 : out_showR [7:0] $end
$var wire 8 ; out_showL [7:0] $end
$var wire 1 < openBtn $end
$var wire 26 = msg [25:0] $end
$var wire 3 > initTime [2:0] $end
$var wire 1 ? hadFinish $end
$var wire 3 @ finishTime [2:0] $end
$var wire 26 A data [25:0] $end
$var wire 1 + d_spinWaterLED $end
$var wire 1 , d_outwaterLED $end
$var wire 1 B cp $end
$var wire 1 C click $end
$var wire 1 D WaterBtn $end
$var wire 10 E LEDMsg [9:0] $end
$scope module b1 $end
$var wire 1 1 btn $end
$var wire 1 B clk $end
$var reg 1 F b1 $end
$var reg 1 G b2 $end
$var reg 1 9 syncBtn $end
$upscope $end
$scope module b2 $end
$var wire 1 2 btn $end
$var wire 1 B clk $end
$var reg 1 H b1 $end
$var reg 1 I b2 $end
$var reg 1 8 syncBtn $end
$upscope $end
$scope module b6 $end
$var wire 1 . btn $end
$var wire 1 B clk $end
$var reg 1 J b1 $end
$var reg 1 K b2 $end
$var reg 1 D syncBtn $end
$upscope $end
$scope module b7 $end
$var wire 1 0 btn $end
$var wire 1 B clk $end
$var reg 1 L b1 $end
$var reg 1 M b2 $end
$var reg 1 < syncBtn $end
$upscope $end
$scope module b8 $end
$var wire 1 / btn $end
$var wire 1 B clk $end
$var reg 1 N b1 $end
$var reg 1 O b2 $end
$var reg 1 C syncBtn $end
$upscope $end
$scope module c $end
$var wire 1 - clk $end
$var reg 1 B cp $end
$var integer 32 P counter [31:0] $end
$upscope $end
$scope module m $end
$var wire 1 C click $end
$var wire 1 B cp $end
$var wire 3 Q setting [2:0] $end
$var wire 1 D waterBtn $end
$var wire 3 R state [2:0] $end
$var wire 26 S outData [25:0] $end
$var wire 26 T data [25:0] $end
$var reg 3 U inWaterTime [2:0] $end
$var reg 3 V setData [2:0] $end
$scope module s $end
$var wire 3 W setData [2:0] $end
$var wire 3 X state [2:0] $end
$var wire 26 Y res [25:0] $end
$var wire 26 Z data [25:0] $end
$upscope $end
$scope module t $end
$var wire 3 [ inWaterTime [2:0] $end
$var wire 3 \ setData [2:0] $end
$var reg 26 ] getData [25:0] $end
$upscope $end
$upscope $end
$scope module rc $end
$var wire 1 B clk $end
$var wire 26 ^ data [25:0] $end
$var wire 3 _ state [2:0] $end
$var wire 1 ` cp $end
$var reg 3 a finishTime [2:0] $end
$var reg 1 ? hadFinish $end
$var reg 3 b initTime [2:0] $end
$var reg 26 c msg [25:0] $end
$scope module s $end
$var wire 1 B clk $end
$var reg 1 ` cp $end
$var integer 32 d count [31:0] $end
$upscope $end
$upscope $end
$scope module stc $end
$var wire 1 B cp $end
$var wire 3 e finishTime [2:0] $end
$var wire 1 ? hadFinish $end
$var wire 3 f initTime [2:0] $end
$var wire 1 < openBtn $end
$var wire 1 9 resetBtn $end
$var wire 1 8 runBtn $end
$var reg 3 g nextState [2:0] $end
$var reg 3 h state [2:0] $end
$upscope $end
$scope module v $end
$var wire 1 B cp $end
$var wire 3 i state [2:0] $end
$var wire 1 ! w_inWaterLED $end
$var wire 1 " w_WLED $end
$var wire 8 j showRight [7:0] $end
$var wire 8 k showLeft [7:0] $end
$var wire 1 # setLED $end
$var wire 6 l right [5:0] $end
$var wire 1 $ r_spinWaterLED $end
$var wire 1 % r_outWaterLED $end
$var wire 1 & r_inWaterLED $end
$var wire 1 ' r_RLED $end
$var wire 1 ( powerLED $end
$var wire 6 m middle [5:0] $end
$var wire 6 n left [5:0] $end
$var wire 6 o inRight [5:0] $end
$var wire 6 p inMiddle [5:0] $end
$var wire 6 q inLeft [5:0] $end
$var wire 10 r data [9:0] $end
$var wire 1 + d_spinWaterLED $end
$var wire 1 , d_outwaterLED $end
$scope module l $end
$var wire 1 B clk $end
$var wire 6 s uCur [5:0] $end
$var wire 6 t uTot [5:0] $end
$var wire 6 u uWat [5:0] $end
$var wire 8 v ySEG_ [7:0] $end
$var wire 8 w yAN_ [7:0] $end
$var wire 3 x xPos [2:0] $end
$scope module vC8 $end
$var wire 1 B clk $end
$var reg 3 y yVal [2:0] $end
$upscope $end
$scope module vDecCur $end
$var wire 6 z uVal [5:0] $end
$var wire 4 { yE2 [3:0] $end
$var wire 4 | yE1 [3:0] $end
$upscope $end
$scope module vDecTot $end
$var wire 6 } uVal [5:0] $end
$var wire 4 ~ yE2 [3:0] $end
$var wire 4 !" yE1 [3:0] $end
$upscope $end
$scope module vDecWat $end
$var wire 6 "" uVal [5:0] $end
$var wire 4 #" yE2 [3:0] $end
$var wire 4 $" yE1 [3:0] $end
$upscope $end
$scope module vPat $end
$var wire 4 %" uVal [3:0] $end
$var reg 8 &" ySEG_ [7:0] $end
$upscope $end
$scope module vPos $end
$var wire 3 '" uPos [2:0] $end
$var wire 8 (" yAN_ [7:0] $end
$upscope $end
$upscope $end
$upscope $end
$scope module vc $end
$var wire 1 B cp $end
$var wire 26 )" msg [25:0] $end
$var wire 3 *" state [2:0] $end
$var wire 6 +" showRight [5:0] $end
$var wire 6 ," showMiddle [5:0] $end
$var wire 6 -" showLeft [5:0] $end
$var wire 10 ." LEDMsg [9:0] $end
$upscope $end
$upscope $end
$upscope $end
$enddefinitions $end
#0
$dumpvars
b0 ."
b0 -"
b0 ,"
b0 +"
b0 *"
b0 )"
b11111110 ("
b0 '"
b10010010 &"
b101 %"
b101 $"
b101 #"
b110111 ""
b101 !"
b101 ~
b110111 }
b101 |
b101 {
b110111 z
b0 y
b0 x
b11111110 w
b10010010 v
b110111 u
b110111 t
b110111 s
b0 r
b0 q
b0 p
b0 o
b110111 n
b110111 m
b110111 l
b10010010 k
b11111110 j
b0 i
b0 h
b0 g
b101 f
b101 e
b0 d
b0 c
b101 b
b101 a
1`
b0 _
bx ^
bx ]
bx \
bx [
bx Z
bx Y
b0 X
bx W
bx V
bx U
bx T
bx S
b0 R
bx Q
b1 P
xO
xN
xM
xL
xK
xJ
xI
xH
xG
xF
b0 E
0D
0C
0B
bx A
b101 @
0?
b101 >
b0 =
0<
b10010010 ;
b11111110 :
09
08
bx 7
b0 6
b0 5
b0 4
b0 3
02
01
00
0/
0.
1-
1,
1+
b10010010 *
b11111110 )
0(
1'
1&
1%
1$
0#
1"
1!
$end
#50
0-
#100
b10 P
1-
#150
0-
#200
b11 P
1-
#250
0-
#300
b100 P
1-
#350
0-
#400
b11111101 )
b11111101 :
b11111101 j
b11111101 w
b11111101 ("
0F
0H
0J
0L
0N
b1 x
b1 y
b1 '"
b1 d
1B
b0 P
1-
#450
0-
#500
b1 P
1-
#550
0-
#600
b10 P
1-
#650
0-
#700
b11 P
1-
#750
0-
#800
b100 P
1-
#850
0-
#900
0B
b0 P
1-
#950
0-
#1000
b1 P
1-
#1050
0-
#1100
b10 P
1-
#1150
0-
#1200
b11 P
1-
#1250
0-
#1300
b100 P
1-
#1350
0-
#1400
b11111111 *
b11111111 ;
b11111111 k
b11111111 v
b11111111 &"
b11111011 )
b11111011 :
b11111011 j
b11111011 w
b11111011 ("
b1111 %"
b10 x
b10 y
b10 '"
0O
0M
0K
0I
0G
b10 d
1B
b0 P
1-
#1450
0-
#1500
b1 P
1-
#1550
0-
#1600
b10 P
1-
#1650
0-
#1700
b11 P
1-
#1750
0-
#1800
b100 P
1-
#1850
0-
#1900
0B
b0 P
1-
#1950
0-
#2000
b1 P
1-
#2050
0-
#2100
b10 P
1-
#2150
0-
#2200
b11 P
1-
#2250
0-
#2300
b100 P
1-
#2350
0-
#2400
b11110111 )
b11110111 :
b11110111 j
b11110111 w
b11110111 ("
b11 x
b11 y
b11 '"
b11 d
1B
b0 P
1-
#2450
0-
#2500
b1 P
1-
#2550
0-
#2600
b10 P
1-
#2650
0-
#2700
b11 P
1-
#2750
0-
#2800
b100 P
1-
#2850
0-
#2900
0B
b0 P
1-
#2950
0-
#3000
b1 P
1-
#3050
0-
#3100
b10 P
1-
#3150
0-
#3200
b11 P
1-
#3250
0-
#3300
b100 P
1-
#3350
0-
#3400
b10010010 *
b10010010 ;
b10010010 k
b10010010 v
b10010010 &"
b11101111 )
b11101111 :
b11101111 j
b11101111 w
b11101111 ("
b101 %"
b100 x
b100 y
b100 '"
b100 d
1B
b0 P
1-
#3450
0-
#3500
b1 P
1-
#3550
0-
#3600
b10 P
1-
#3650
0-
#3700
b11 P
1-
#3750
0-
#3800
b100 P
1-
#3850
0-
#3900
0B
b0 P
1-
#3950
0-
#4000
b1 P
1-
#4050
0-
#4100
b10 P
1-
#4150
0-
#4200
b11 P
1-
#4250
0-
#4300
b100 P
1-
#4350
0-
#4400
b11011111 )
b11011111 :
b11011111 j
b11011111 w
b11011111 ("
b101 x
b101 y
b101 '"
0`
b0 d
1B
b0 P
1-
#4450
0-
#4500
b1 P
1-
#4550
0-
#4600
b10 P
1-
#4650
0-
#4700
b11 P
1-
#4750
0-
#4800
b100 P
1-
#4850
0-
#4900
0B
b0 P
1-
#4950
0-
#5000
b1 P
1-
#5050
0-
#5100
b10 P
1-
#5150
0-
#5200
b11 P
1-
#5250
0-
#5300
b100 P
1-
#5350
0-
#5400
b10111111 )
b10111111 :
b10111111 j
b10111111 w
b10111111 ("
b110 x
b110 y
b110 '"
b1 d
1B
b0 P
1-
#5450
0-
#5500
b1 P
1-
#5550
0-
#5600
b10 P
1-
#5650
0-
#5700
b11 P
1-
#5750
0-
#5800
b100 P
1-
#5850
0-
#5900
0B
b0 P
1-
#5950
0-
#6000
b1 P
1-
#6050
0-
#6100
b10 P
1-
#6150
0-
#6200
b11 P
1-
#6250
0-
#6300
b100 P
1-
#6350
0-
#6400
b1111111 )
b1111111 :
b1111111 j
b1111111 w
b1111111 ("
b111 x
b111 y
b111 '"
b10 d
1B
b0 P
1-
#6450
0-
#6500
b1 P
1-
#6550
0-
#6600
b10 P
1-
#6650
0-
#6700
b11 P
1-
#6750
0-
#6800
b100 P
1-
#6850
0-
#6900
0B
b0 P
1-
#6950
0-
#7000
b1 P
1-
#7050
0-
#7100
b10 P
1-
#7150
0-
#7200
b11 P
1-
#7250
0-
#7300
b100 P
1-
#7350
0-
#7400
b11111110 )
b11111110 :
b11111110 j
b11111110 w
b11111110 ("
b0 x
b0 y
b0 '"
b11 d
1B
b0 P
1-
#7450
0-
#7500
b1 P
1-
#7550
0-
#7600
b10 P
1-
#7650
0-
#7700
b11 P
1-
#7750
0-
#7800
b100 P
1-
#7850
0-
#7900
0B
b0 P
1-
#7950
0-
#8000
b1 P
1-
#8050
0-
#8100
b10 P
1-
#8150
0-
#8200
b11 P
1-
#8250
0-
#8300
b100 P
1-
#8350
0-
#8400
b11111101 )
b11111101 :
b11111101 j
b11111101 w
b11111101 ("
b1 x
b1 y
b1 '"
b100 d
1B
b0 P
1-
#8450
0-
#8500
b1 P
1-
#8550
0-
#8600
b10 P
1-
#8650
0-
#8700
b11 P
1-
#8750
0-
#8800
b100 P
1-
#8850
0-
#8900
0B
b0 P
1-
#8950
0-
#9000
b1 P
1-
#9050
0-
#9100
b10 P
1-
#9150
0-
#9200
b11 P
1-
#9250
0-
#9300
b100 P
1-
#9350
0-
#9400
b11111111 *
b11111111 ;
b11111111 k
b11111111 v
b11111111 &"
b0xxxxxxxx E
b0xxxxxxxx r
b0xxxxxxxx ."
b0xxxx 5
b0xxxx p
b0xxxx ,"
bx 6
bx q
bx -"
b0xxx 4
b0xxx o
b0xxx +"
b11111011 )
b11111011 :
b11111011 j
b11111011 w
b11111011 ("
bx =
bx c
bx )"
b1111 %"
b10 x
b10 y
b10 '"
1`
b0 d
1B
b0 P
1-
#9450
0-
#9500
b1 P
1-
#9550
0-
#9600
b10 P
1-
#9650
0-
#9700
b11 P
1-
#9750
0-
#9800
b100 P
1-
#9850
0-
#9900
0B
b0 P
1-
#9950
0-
#10000
b1 P
1-
#10050
0-
#10100
b10 P
1-
#10150
0-
#10200
b11 P
1-
